hello.py
mgorav_hellworld-0.0.1.dist-info/METADATA
mgorav_hellworld-0.0.1.dist-info/WHEEL
mgorav_hellworld-0.0.1.dist-info/top_level.txt
mgorav_hellworld-0.0.1.dist-info/RECORD
